{
    "Ar36": {
        "error": 0.00027599002402122722, 
        "fit": "parabolic", 
        "value": 0.015355371843041981
    }, 
    "Ar37": {
        "error": 0.01210094878878573, 
        "fit": "linear", 
        "value": 0.34595206797576766
    }, 
    "Ar38": {
        "error": 0.028153983178127184, 
        "fit": "linear", 
        "value": 2.9003578911545898
    }, 
    "Ar39": {
        "error": 0.023805852173918316, 
        "fit": "parabolic", 
        "value": 243.66193469431937
    }, 
    "Ar40": {
        "error": 0.089233352798597537, 
        "fit": "parabolic", 
        "value": 1940.0728834861616
    }, 
    "Ar41": {
        "error": 0.0050234706347739603, 
        "fit": "average_SEM", 
        "value": -0.078469887269496941
    }
}