{
    "Ar36": {
        "error": 0.00030793734227684737, 
        "fit": "parabolic", 
        "value": 0.014735144330988468
    }, 
    "Ar37": {
        "error": 0.012471406077248021, 
        "fit": "linear", 
        "value": 0.31876838550783004
    }, 
    "Ar38": {
        "error": 0.023005632525277563, 
        "fit": "linear", 
        "value": 2.4748127969579876
    }, 
    "Ar39": {
        "error": 0.02297307457536471, 
        "fit": "parabolic", 
        "value": 208.41275600072618
    }, 
    "Ar40": {
        "error": 0.082289055153129287, 
        "fit": "parabolic", 
        "value": 1661.9353048335975
    }, 
    "Ar41": {
        "error": 0.0047188029662900491, 
        "fit": "average_SEM", 
        "value": -0.065157595269372162
    }
}