{
    "Ar36": {
        "error": 0.0022361477190533325, 
        "fit": "parabolic", 
        "value": 0.028515088348786716
    }, 
    "Ar37": {
        "error": 0.14002894252791731, 
        "fit": "linear", 
        "value": 0.64219073130166959
    }, 
    "Ar38": {
        "error": 0.12902307730524021, 
        "fit": "linear", 
        "value": 2.6005426345336415
    }, 
    "Ar39": {
        "error": 0.1405702861378296, 
        "fit": "parabolic", 
        "value": 199.73821002913735
    }, 
    "Ar40": {
        "error": 0.53570357335010788, 
        "fit": "parabolic", 
        "value": 1607.2675911436104
    }, 
    "Ar41": {
        "error": 0.11673176378783724, 
        "fit": "average_SEM", 
        "value": -0.079486038179529719
    }
}