{
    "Ar36": {
        "error": 0.00085478300173422389, 
        "fit": "parabolic", 
        "value": 0.00073192617064534457
    }, 
    "Ar37": {
        "error": 0.13119013727538556, 
        "fit": "linear", 
        "value": 0.17361218539549977
    }, 
    "Ar38": {
        "error": 0.173197879603015, 
        "fit": "linear", 
        "value": 0.10774407099257668
    }, 
    "Ar39": {
        "error": 0.058742883948762606, 
        "fit": "parabolic", 
        "value": 0.018297521584285957
    }, 
    "Ar40": {
        "error": 0.13471307214152919, 
        "fit": "parabolic", 
        "value": 0.28223116868792492
    }, 
    "Ar41": {
        "error": 0.12356342274276763, 
        "fit": "average_SEM", 
        "value": -0.098659844758367393
    }
}